{
  "errno": 0,
  "data": {
    "list": [
      {
        "defaultValue": "",
        "key": "region",
        "type": "radio",
        "value": "region",
        "title": "地区",
        "children": [
          {
            "title": "区域",
            "key": "region",
            "type": "radio",
            "defaultValue": "2",
            "value": "",
            "children": [
              {
                "title": "全上海",
                "key": "town",
                "type": "unlimit",
                "defaultValue": "",
                "value": ""
              },
              {
                "title": "浦东",
                "key": "town",
                "type": "checkbox",
                "defaultValue": "",
                "value": "浦东"
              },
              {
                "title": "闵行",
                "key": "town",
                "type": "checkbox",
                "defaultValue": "",
                "value": "闵行"
              },
              {
                "title": "松江",
                "key": "town",
                "type": "checkbox",
                "defaultValue": "",
                "value": "松江"
              },
              {
                "title": "宝山",
                "key": "town",
                "type": "checkbox",
                "defaultValue": "",
                "value": "宝山"
              },
              {
                "title": "嘉定",
                "key": "town",
                "type": "checkbox",
                "defaultValue": "",
                "value": "嘉定"
              },
              {
                "title": "徐汇",
                "key": "town",
                "type": "checkbox",
                "defaultValue": "",
                "value": "徐汇"
              },
              {
                "title": "青浦",
                "key": "town",
                "type": "checkbox",
                "defaultValue": "",
                "value": "青浦"
              },
              {
                "title": "静安",
                "key": "town",
                "type": "checkbox",
                "defaultValue": "",
                "value": "静安"
              },
              {
                "title": "普陀",
                "key": "town",
                "type": "checkbox",
                "defaultValue": "",
                "value": "普陀"
              },
              {
                "title": "杨浦",
                "key": "town",
                "type": "checkbox",
                "defaultValue": "",
                "value": "杨浦"
              },
              {
                "title": "奉贤",
                "key": "town",
                "type": "checkbox",
                "defaultValue": "",
                "value": "奉贤"
              },
              {
                "title": "黄浦",
                "key": "town",
                "type": "checkbox",
                "defaultValue": "",
                "value": "黄浦"
              },
              {
                "title": "虹口",
                "key": "town",
                "type": "checkbox",
                "defaultValue": "",
                "value": "虹口"
              },
              {
                "title": "长宁",
                "key": "town",
                "type": "checkbox",
                "defaultValue": "",
                "value": "长宁"
              },
              {
                "title": "金山",
                "key": "town",
                "type": "checkbox",
                "defaultValue": "",
                "value": "金山"
              },
              {
                "title": "崇明",
                "key": "town",
                "type": "checkbox",
                "defaultValue": "",
                "value": "崇明"
              },
              {
                "title": "上海周边",
                "key": "town",
                "type": "checkbox",
                "defaultValue": "",
                "value": "上海周边"
              }
            ]
          },
          {
            "title": "地铁",
            "key": "subway",
            "type": "radio",
            "defaultValue": "",
            "value": "",
            "children": [
              {
                "title": "1号线",
                "key": "station",
                "type": "radio",
                "defaultValue": "",
                "value": "1",
                "children": [
                  {
                    "title": "富锦路",
                    "key": "富锦路",
                    "type": "checkbox",
                    "defaultValue": "",
                    "value": "富锦路"
                  },
                  {
                    "title": "友谊西路",
                    "key": "友谊西路",
                    "type": "checkbox",
                    "defaultValue": "",
                    "value": "友谊西路"
                  },
                  {
                    "title": "宝安公路",
                    "key": "宝安公路",
                    "type": "checkbox",
                    "defaultValue": "",
                    "value": "宝安公路"
                  }
                ]
              },
              {
                "title": "2号线",
                "key": "station",
                "type": "radio",
                "defaultValue": "",
                "value": "2"
              },
              {
                "title": "3号线",
                "key": "station",
                "type": "radio",
                "defaultValue": "",
                "value": "3"
              },
              {
                "title": "4号线",
                "key": "station",
                "type": "radio",
                "defaultValue": "",
                "value": "4"
              },
              {
                "title": "5号线",
                "key": "station",
                "type": "radio",
                "defaultValue": "",
                "value": "5"
              },
              {
                "title": "6号线",
                "key": "station",
                "type": "radio",
                "defaultValue": "",
                "value": "6"
              },
              {
                "title": "7号线",
                "key": "station",
                "type": "radio",
                "defaultValue": "",
                "value": "7"
              },
              {
                "title": "8号线",
                "key": "station",
                "type": "radio",
                "defaultValue": "",
                "value": "8"
              },
              {
                "title": "9号线",
                "key": "station",
                "type": "radio",
                "defaultValue": "",
                "value": "9"
              },
              {
                "title": "10号线",
                "key": "station",
                "type": "radio",
                "defaultValue": "",
                "value": "10",
                "children": [
                  {
                    "title": "基隆路",
                    "key": "基隆路",
                    "type": "checkbox",
                    "defaultValue": "",
                    "value": "基隆路"
                  }
                ]
              },
              {
                "title": "11号线",
                "key": "station",
                "type": "radio",
                "defaultValue": "",
                "value": "11"
              },
              {
                "title": "12号线",
                "key": "station",
                "type": "radio",
                "defaultValue": "",
                "value": "12"
              },
              {
                "title": "13号线",
                "key": "station",
                "type": "radio",
                "defaultValue": "",
                "value": "13"
              },
              {
                "title": "14号线",
                "key": "station",
                "type": "radio",
                "defaultValue": "",
                "value": "14"
              },
              {
                "title": "15号线",
                "key": "station",
                "type": "radio",
                "defaultValue": "",
                "value": "15"
              },
              {
                "title": "16号线",
                "key": "station",
                "type": "radio",
                "defaultValue": "",
                "value": "16"
              },
              {
                "title": "17号线",
                "key": "station",
                "type": "radio",
                "defaultValue": "",
                "value": "17"
              },
              {
                "title": "18号线",
                "key": "station",
                "type": "radio",
                "defaultValue": "",
                "value": "18"
              }
            ]
          }
        ]
      },
      {
        "title": "租金",
        "key": "price",
        "type": "checkbox",
        "defaultValue": "",
        "value": "",
        "children": [
          {
            "title": "不限",
            "key": "",
            "type": "unlimit",
            "defaultValue": "",
            "value": "0"
          },
          {
            "title": "1500元以下",
            "key": "",
            "type": "radio",
            "defaultValue": "",
            "value": "0:1500"
          },
          {
            "title": "1500-2000元",
            "key": "",
            "type": "radio",
            "defaultValue": "",
            "value": "1500:2000"
          },
          {
            "title": "2000-3000元",
            "key": "",
            "type": "radio",
            "defaultValue": "",
            "value": "2000:3000"
          },
          {
            "title": "3000-5000元",
            "key": "",
            "type": "radio",
            "defaultValue": "",
            "value": "3000:5000"
          },
          {
            "title": "5000-8000元",
            "key": "",
            "type": "radio",
            "defaultValue": "",
            "value": "5000:8000"
          },
          {
            "title": "8000元以上",
            "key": "",
            "type": "radio",
            "defaultValue": "",
            "value": "8000:999999"
          },
          {
            "defaultValue": "",
            "ext": {"min": 0, "max": 999999, "unit": "元"},
            "children": [],
            "key": "",
            "type": "range",
            "value": "",
            "title": "租金"
          }
        ]
      },
      {
        "title": "居室",
        "defaultValue": "",
        "key": "room",
        "type": "checkbox",
        "value": "",
        "children": [
          {
            "title": "户型",
            "key": "户型",
            "type": "radio",
            "defaultValue": "",
            "value": "",
            "children": [
              {
                "title": "不限",
                "key": "",
                "type": "unlimit",
                "defaultValue": "",
                "value": ""
              },
              {
                "title": "一室",
                "key": "",
                "type": "checkbox",
                "defaultValue": "",
                "value": "1"
              },
              {
                "title": "两室",
                "key": "",
                "type": "checkbox",
                "defaultValue": "",
                "value": "2"
              },
              {
                "title": "三室",
                "key": "",
                "type": "checkbox",
                "defaultValue": "",
                "value": "3"
              },
              {
                "title": "四室及以上",
                "key": "",
                "type": "checkbox",
                "defaultValue": "",
                "value": "4"
              }
            ]
          }
        ]
      },
      {
        "title": "类型",
        "defaultValue": "",
        "key": "rentType",
        "type": "radio",
        "value": "",
        "children": [
          {
            "title": "类型",
            "key": "类型",
            "type": "radio",
            "defaultValue": "",
            "value": "",
            "children": [
              {
                "title": "不限",
                "key": "",
                "type": "unlimit",
                "defaultValue": "",
                "value": ""
              },
              {
                "title": "合租",
                "key": "",
                "type": "checkbox",
                "defaultValue": "",
                "value": "1"
              },
              {
                "title": "整套出租",
                "key": "",
                "type": "checkbox",
                "defaultValue": "",
                "value": "3"
              },
              {
                "title": "公寓",
                "key": "",
                "type": "checkbox",
                "defaultValue": "",
                "value": "4"
              }
            ]
          }
        ]
      }
    ]
  }
}
